check_symbols/__init__.py
check_symbols/colour.py
check_symbols/main.py
check_symbols/paths.py
check_symbols/version.py
check_symbols/version.txt
check_symbols-0.1.0.dist-info/LICENSE.txt
check_symbols-0.1.0.dist-info/METADATA
check_symbols-0.1.0.dist-info/WHEEL
check_symbols-0.1.0.dist-info/entry_points.txt
check_symbols-0.1.0.dist-info/top_level.txt
check_symbols-0.1.0.dist-info/zip-safe
check_symbols-0.1.0.dist-info/RECORD
