Metadata-Version: 2.1
Name: check-symbols
Version: 0.1.0
Summary: Command-line utility for checking ELF symbols.
Author-email: Mark Gillard <mark.gillard@outlook.com.au>
License: MIT
Project-URL: Source, https://github.com/marzer/check-symbols
Project-URL: Tracker, https://github.com/marzer/check-symbols/issues
Project-URL: Funding, https://github.com/sponsors/marzer
Keywords: c++,check-symbols,elf,symbols,binary,executable,shared library
Classifier: Development Status :: 3 - Alpha
Classifier: License :: OSI Approved :: MIT License
Classifier: Programming Language :: C
Classifier: Programming Language :: C++
Classifier: Topic :: Software Development
Classifier: Topic :: Software Development :: Testing
Classifier: Topic :: Software Development :: Compilers
Classifier: Topic :: Software Development :: Build Tools
Classifier: Topic :: Software Development :: Bug Tracking
Classifier: Topic :: Utilities
Requires-Python: >=3.8
License-File: LICENSE.txt
Requires-Dist: misk >=0.8.1
Requires-Dist: colorama
